asananas/__init__.py
asananas/_version.py
asananas/allocation_management.py
asananas/asana_connector.py
asananas/asana_linear_bridge.py
asananas/linear_connector.py
asananas/assets/asana_example_task.png
asananas/assets/asana_linear_mapping.png
asananas/assets/demo_fig.html
asananas/assets/logo.png
asananas/assets/logo2.png
asananas/assets/logo3.png
asananas/assets/resource_allocation_example.png
asananas/dashboard/__init__.py
asananas/dashboard/cli.py
asananas/dashboard/main.py
asananas-0.5.0.dist-info/LICENSE
asananas-0.5.0.dist-info/METADATA
asananas-0.5.0.dist-info/WHEEL
asananas-0.5.0.dist-info/entry_points.txt
asananas-0.5.0.dist-info/top_level.txt
asananas-0.5.0.dist-info/RECORD
