Metadata-Version: 2.1
Name: asananas
Version: 0.5.0
Summary: Asananas helps you with your project management in Asana.
Author-email: Christian Brendel <brendel.chris@gmail.com>
License: MIT License
Project-URL: Homepage, https://github.com/christianbrendel/asananas
Keywords: asana,project-management,dashboard,linear
Classifier: License :: OSI Approved :: MIT License
Classifier: Programming Language :: Python :: 3
Classifier: Operating System :: OS Independent
Requires-Python: >=3.6
License-File: LICENSE
Requires-Dist: asana (>=1.0.0)
Requires-Dist: requests
Requires-Dist: loguru
Requires-Dist: pandas
Requires-Dist: streamlit (>=1.0.0)
Requires-Dist: plotly
Provides-Extra: dev
Requires-Dist: black ; extra == 'dev'
Requires-Dist: flake8 ; extra == 'dev'
Requires-Dist: ipykernel ; extra == 'dev'
Requires-Dist: nbformat (>=4.2.0) ; extra == 'dev'
Requires-Dist: isort ; extra == 'dev'
Requires-Dist: pre-commit ; extra == 'dev'
Requires-Dist: pydocstyle ; extra == 'dev'
Requires-Dist: build ; extra == 'dev'
Requires-Dist: twine ; extra == 'dev'
